<?xml version="1.0" encoding="UTF-8"?><?xml-stylesheet type='text/xsl' href='_UpgradeReport_Files/UpgradeReport.xslt'?><UpgradeLog>
<Properties><Property Name="Solution" Value="Almacen">
</Property><Property Name="Archivo de la solución" Value="C:\Users\Eduardo\Google Drive\Esperanza\Almacen\Almacen.sln">
</Property><Property Name="Archivo de opciones de usuario" Value="C:\Users\Eduardo\Google Drive\Esperanza\Almacen\Almacen.suo">
</Property><Property Name="Date" Value="viernes, 6 de noviembre de 2015">
</Property><Property Name="Time" Value="07:25 a. m.">
</Property></Properties><Event ErrorLevel="0" Project="" Source="Almacen.sln" Description="La copia C:\Users\Eduardo\Google Drive\Esperanza\Almacen\Backup\Almacen.sln del archivo se ha realizado correctamente">
</Event><Event ErrorLevel="0" Project="" Source="Almacen.suo" Description="La copia C:\Users\Eduardo\Google Drive\Esperanza\Almacen\Backup\Almacen.suo del archivo se ha realizado correctamente">
</Event><Event ErrorLevel="0" Project="Almacen" Source="Almacen.vbproj" Description="Se realizó correctamente la copia de seguridad del archivo de proyecto C:\Users\Eduardo\Google Drive\Esperanza\Almacen\Backup\Almacen.vbproj">
</Event><Event ErrorLevel="0" Project="Almacen" Source="Almacen.vbproj.user" Description="La copia de seguridad C:\Users\Eduardo\Google Drive\Esperanza\Almacen\Backup\Almacen.vbproj.user del archivo se ha creado correctamente">
</Event><Event ErrorLevel="0" Project="Almacen" Source="Catalogo\Agrupar_productos.Designer.vb" Description="Se realizó correctamente la copia de seguridad del archivo C:\Users\Eduardo\Google Drive\Esperanza\Almacen\Backup\Catalogo\Agrupar_productos.Designer.vb">
</Event><Event ErrorLevel="0" Project="Almacen" Source="Catalogo\Agrupar_productos.vb" Description="Se realizó correctamente la copia de seguridad del archivo C:\Users\Eduardo\Google Drive\Esperanza\Almacen\Backup\Catalogo\Agrupar_productos.vb">
</Event><Event ErrorLevel="0" Project="Almacen" Source="Catalogo\Medicos.Designer.vb" Description="Se realizó correctamente la copia de seguridad del archivo C:\Users\Eduardo\Google Drive\Esperanza\Almacen\Backup\Catalogo\Medicos.Designer.vb">
</Event><Event ErrorLevel="0" Project="Almacen" Source="Catalogo\Medicos.vb" Description="Se realizó correctamente la copia de seguridad del archivo C:\Users\Eduardo\Google Drive\Esperanza\Almacen\Backup\Catalogo\Medicos.vb">
</Event><Event ErrorLevel="0" Project="Almacen" Source="Catalogo\productos_nuevo.Designer.vb" Description="Se realizó correctamente la copia de seguridad del archivo C:\Users\Eduardo\Google Drive\Esperanza\Almacen\Backup\Catalogo\productos_nuevo.Designer.vb">
</Event><Event ErrorLevel="0" Project="Almacen" Source="Catalogo\productos_nuevo.vb" Description="Se realizó correctamente la copia de seguridad del archivo C:\Users\Eduardo\Google Drive\Esperanza\Almacen\Backup\Catalogo\productos_nuevo.vb">
</Event><Event ErrorLevel="0" Project="Almacen" Source="Catalogo\productos_relacion.Designer.vb" Description="Se realizó correctamente la copia de seguridad del archivo C:\Users\Eduardo\Google Drive\Esperanza\Almacen\Backup\Catalogo\productos_relacion.Designer.vb">
</Event><Event ErrorLevel="0" Project="Almacen" Source="Catalogo\productos_relacion.vb" Description="Se realizó correctamente la copia de seguridad del archivo C:\Users\Eduardo\Google Drive\Esperanza\Almacen\Backup\Catalogo\productos_relacion.vb">
</Event><Event ErrorLevel="0" Project="Almacen" Source="clinica.vb" Description="Se realizó correctamente la copia de seguridad del archivo C:\Users\Eduardo\Google Drive\Esperanza\Almacen\Backup\clinica.vb">
</Event><Event ErrorLevel="0" Project="Almacen" Source="clinicaDataSet.Designer.vb" Description="Se realizó correctamente la copia de seguridad del archivo C:\Users\Eduardo\Google Drive\Esperanza\Almacen\Backup\clinicaDataSet.Designer.vb">
</Event><Event ErrorLevel="0" Project="Almacen" Source="clinicaDataSet.vb" Description="Se realizó correctamente la copia de seguridad del archivo C:\Users\Eduardo\Google Drive\Esperanza\Almacen\Backup\clinicaDataSet.vb">
</Event><Event ErrorLevel="0" Project="Almacen" Source="compras\entradas_nueva.Designer.vb" Description="Se realizó correctamente la copia de seguridad del archivo C:\Users\Eduardo\Google Drive\Esperanza\Almacen\Backup\compras\entradas_nueva.Designer.vb">
</Event><Event ErrorLevel="0" Project="Almacen" Source="compras\entradas_nueva.vb" Description="Se realizó correctamente la copia de seguridad del archivo C:\Users\Eduardo\Google Drive\Esperanza\Almacen\Backup\compras\entradas_nueva.vb">
</Event><Event ErrorLevel="0" Project="Almacen" Source="compras\Entrasdas_consulta.Designer.vb" Description="Se realizó correctamente la copia de seguridad del archivo C:\Users\Eduardo\Google Drive\Esperanza\Almacen\Backup\compras\Entrasdas_consulta.Designer.vb">
</Event><Event ErrorLevel="0" Project="Almacen" Source="compras\Entrasdas_consulta.vb" Description="Se realizó correctamente la copia de seguridad del archivo C:\Users\Eduardo\Google Drive\Esperanza\Almacen\Backup\compras\Entrasdas_consulta.vb">
</Event><Event ErrorLevel="0" Project="Almacen" Source="inventarios\capturar_inventarios.Designer.vb" Description="Se realizó correctamente la copia de seguridad del archivo C:\Users\Eduardo\Google Drive\Esperanza\Almacen\Backup\inventarios\capturar_inventarios.Designer.vb">
</Event><Event ErrorLevel="0" Project="Almacen" Source="inventarios\capturar_inventarios.vb" Description="Se realizó correctamente la copia de seguridad del archivo C:\Users\Eduardo\Google Drive\Esperanza\Almacen\Backup\inventarios\capturar_inventarios.vb">
</Event><Event ErrorLevel="0" Project="Almacen" Source="inventarios\inventarios_hojas.Designer.vb" Description="Se realizó correctamente la copia de seguridad del archivo C:\Users\Eduardo\Google Drive\Esperanza\Almacen\Backup\inventarios\inventarios_hojas.Designer.vb">
</Event><Event ErrorLevel="0" Project="Almacen" Source="inventarios\inventarios_hojas.vb" Description="Se realizó correctamente la copia de seguridad del archivo C:\Users\Eduardo\Google Drive\Esperanza\Almacen\Backup\inventarios\inventarios_hojas.vb">
</Event><Event ErrorLevel="0" Project="Almacen" Source="inventarios\inv_calcula_Existencia.Designer.vb" Description="Se realizó correctamente la copia de seguridad del archivo C:\Users\Eduardo\Google Drive\Esperanza\Almacen\Backup\inventarios\inv_calcula_Existencia.Designer.vb">
</Event><Event ErrorLevel="0" Project="Almacen" Source="inventarios\inv_calcula_Existencia.vb" Description="Se realizó correctamente la copia de seguridad del archivo C:\Users\Eduardo\Google Drive\Esperanza\Almacen\Backup\inventarios\inv_calcula_Existencia.vb">
</Event><Event ErrorLevel="0" Project="Almacen" Source="inventarios\Inv_crear_hoja.Designer.vb" Description="Se realizó correctamente la copia de seguridad del archivo C:\Users\Eduardo\Google Drive\Esperanza\Almacen\Backup\inventarios\Inv_crear_hoja.Designer.vb">
</Event><Event ErrorLevel="0" Project="Almacen" Source="inventarios\Inv_crear_hoja.vb" Description="Se realizó correctamente la copia de seguridad del archivo C:\Users\Eduardo\Google Drive\Esperanza\Almacen\Backup\inventarios\Inv_crear_hoja.vb">
</Event><Event ErrorLevel="0" Project="Almacen" Source="inventarios\reporte_de_inventario.Designer.vb" Description="Se realizó correctamente la copia de seguridad del archivo C:\Users\Eduardo\Google Drive\Esperanza\Almacen\Backup\inventarios\reporte_de_inventario.Designer.vb">
</Event><Event ErrorLevel="0" Project="Almacen" Source="inventarios\reporte_de_inventario.vb" Description="Se realizó correctamente la copia de seguridad del archivo C:\Users\Eduardo\Google Drive\Esperanza\Almacen\Backup\inventarios\reporte_de_inventario.vb">
</Event><Event ErrorLevel="0" Project="Almacen" Source="inventarios\kardex.Designer.vb" Description="Se realizó correctamente la copia de seguridad del archivo C:\Users\Eduardo\Google Drive\Esperanza\Almacen\Backup\inventarios\kardex.Designer.vb">
</Event><Event ErrorLevel="0" Project="Almacen" Source="inventarios\kardex.vb" Description="Se realizó correctamente la copia de seguridad del archivo C:\Users\Eduardo\Google Drive\Esperanza\Almacen\Backup\inventarios\kardex.vb">
</Event><Event ErrorLevel="0" Project="Almacen" Source="recetas\lotes_modificar_fechas.Designer.vb" Description="Se realizó correctamente la copia de seguridad del archivo C:\Users\Eduardo\Google Drive\Esperanza\Almacen\Backup\recetas\lotes_modificar_fechas.Designer.vb">
</Event><Event ErrorLevel="0" Project="Almacen" Source="recetas\lotes_modificar_fechas.vb" Description="Se realizó correctamente la copia de seguridad del archivo C:\Users\Eduardo\Google Drive\Esperanza\Almacen\Backup\recetas\lotes_modificar_fechas.vb">
</Event><Event ErrorLevel="0" Project="Almacen" Source="recetas\recetas.Designer.vb" Description="Se realizó correctamente la copia de seguridad del archivo C:\Users\Eduardo\Google Drive\Esperanza\Almacen\Backup\recetas\recetas.Designer.vb">
</Event><Event ErrorLevel="0" Project="Almacen" Source="recetas\recetas.vb" Description="Se realizó correctamente la copia de seguridad del archivo C:\Users\Eduardo\Google Drive\Esperanza\Almacen\Backup\recetas\recetas.vb">
</Event><Event ErrorLevel="0" Project="Almacen" Source="recetas\recetas_Asignar.Designer.vb" Description="Se realizó correctamente la copia de seguridad del archivo C:\Users\Eduardo\Google Drive\Esperanza\Almacen\Backup\recetas\recetas_Asignar.Designer.vb">
</Event><Event ErrorLevel="0" Project="Almacen" Source="recetas\recetas_Asignar.vb" Description="Se realizó correctamente la copia de seguridad del archivo C:\Users\Eduardo\Google Drive\Esperanza\Almacen\Backup\recetas\recetas_Asignar.vb">
</Event><Event ErrorLevel="0" Project="Almacen" Source="recetas\recetas_modificar.Designer.vb" Description="Se realizó correctamente la copia de seguridad del archivo C:\Users\Eduardo\Google Drive\Esperanza\Almacen\Backup\recetas\recetas_modificar.Designer.vb">
</Event><Event ErrorLevel="0" Project="Almacen" Source="recetas\recetas_modificar.vb" Description="Se realizó correctamente la copia de seguridad del archivo C:\Users\Eduardo\Google Drive\Esperanza\Almacen\Backup\recetas\recetas_modificar.vb">
</Event><Event ErrorLevel="0" Project="Almacen" Source="recetas_dataset.Designer.vb" Description="Se realizó correctamente la copia de seguridad del archivo C:\Users\Eduardo\Google Drive\Esperanza\Almacen\Backup\recetas_dataset.Designer.vb">
</Event><Event ErrorLevel="0" Project="Almacen" Source="recetas\recetas_poner_factura.Designer.vb" Description="Se realizó correctamente la copia de seguridad del archivo C:\Users\Eduardo\Google Drive\Esperanza\Almacen\Backup\recetas\recetas_poner_factura.Designer.vb">
</Event><Event ErrorLevel="0" Project="Almacen" Source="recetas\recetas_poner_factura.vb" Description="Se realizó correctamente la copia de seguridad del archivo C:\Users\Eduardo\Google Drive\Esperanza\Almacen\Backup\recetas\recetas_poner_factura.vb">
</Event><Event ErrorLevel="0" Project="Almacen" Source="sdk_inventarios.vb" Description="Se realizó correctamente la copia de seguridad del archivo C:\Users\Eduardo\Google Drive\Esperanza\Almacen\Backup\sdk_inventarios.vb">
</Event><Event ErrorLevel="0" Project="Almacen" Source="Stocks\hoja_gastos.Designer.vb" Description="Se realizó correctamente la copia de seguridad del archivo C:\Users\Eduardo\Google Drive\Esperanza\Almacen\Backup\Stocks\hoja_gastos.Designer.vb">
</Event><Event ErrorLevel="0" Project="Almacen" Source="Stocks\hoja_gastos.vb" Description="Se realizó correctamente la copia de seguridad del archivo C:\Users\Eduardo\Google Drive\Esperanza\Almacen\Backup\Stocks\hoja_gastos.vb">
</Event><Event ErrorLevel="0" Project="Almacen" Source="Stocks\hoja_honorarios.Designer.vb" Description="Se realizó correctamente la copia de seguridad del archivo C:\Users\Eduardo\Google Drive\Esperanza\Almacen\Backup\Stocks\hoja_honorarios.Designer.vb">
</Event><Event ErrorLevel="0" Project="Almacen" Source="Stocks\hoja_honorarios.vb" Description="Se realizó correctamente la copia de seguridad del archivo C:\Users\Eduardo\Google Drive\Esperanza\Almacen\Backup\Stocks\hoja_honorarios.vb">
</Event><Event ErrorLevel="0" Project="Almacen" Source="Stocks\hoja_honorarios_pediatricos.Designer.vb" Description="Se realizó correctamente la copia de seguridad del archivo C:\Users\Eduardo\Google Drive\Esperanza\Almacen\Backup\Stocks\hoja_honorarios_pediatricos.Designer.vb">
</Event><Event ErrorLevel="0" Project="Almacen" Source="Stocks\hoja_honorarios_pediatricos.vb" Description="Se realizó correctamente la copia de seguridad del archivo C:\Users\Eduardo\Google Drive\Esperanza\Almacen\Backup\Stocks\hoja_honorarios_pediatricos.vb">
</Event><Event ErrorLevel="0" Project="Almacen" Source="Stocks\stocks_definir.Designer.vb" Description="Se realizó correctamente la copia de seguridad del archivo C:\Users\Eduardo\Google Drive\Esperanza\Almacen\Backup\Stocks\stocks_definir.Designer.vb">
</Event><Event ErrorLevel="0" Project="Almacen" Source="Stocks\stocks_definir.vb" Description="Se realizó correctamente la copia de seguridad del archivo C:\Users\Eduardo\Google Drive\Esperanza\Almacen\Backup\Stocks\stocks_definir.vb">
</Event><Event ErrorLevel="0" Project="Almacen" Source="Surtidos\consultar_consumo_de_consumibles.Designer.vb" Description="Se realizó correctamente la copia de seguridad del archivo C:\Users\Eduardo\Google Drive\Esperanza\Almacen\Backup\Surtidos\consultar_consumo_de_consumibles.Designer.vb">
</Event><Event ErrorLevel="0" Project="Almacen" Source="Surtidos\consultar_consumo_de_consumibles.vb" Description="Se realizó correctamente la copia de seguridad del archivo C:\Users\Eduardo\Google Drive\Esperanza\Almacen\Backup\Surtidos\consultar_consumo_de_consumibles.vb">
</Event><Event ErrorLevel="0" Project="Almacen" Source="Surtidos\Consumos.Designer.vb" Description="Se realizó correctamente la copia de seguridad del archivo C:\Users\Eduardo\Google Drive\Esperanza\Almacen\Backup\Surtidos\Consumos.Designer.vb">
</Event><Event ErrorLevel="0" Project="Almacen" Source="Surtidos\Consumos.vb" Description="Se realizó correctamente la copia de seguridad del archivo C:\Users\Eduardo\Google Drive\Esperanza\Almacen\Backup\Surtidos\Consumos.vb">
</Event><Event ErrorLevel="0" Project="Almacen" Source="main.vb" Description="Se realizó correctamente la copia de seguridad del archivo C:\Users\Eduardo\Google Drive\Esperanza\Almacen\Backup\main.vb">
</Event><Event ErrorLevel="0" Project="Almacen" Source="main.Designer.vb" Description="Se realizó correctamente la copia de seguridad del archivo C:\Users\Eduardo\Google Drive\Esperanza\Almacen\Backup\main.Designer.vb">
</Event><Event ErrorLevel="0" Project="Almacen" Source="My Project\AssemblyInfo.vb" Description="Se realizó correctamente la copia de seguridad del archivo C:\Users\Eduardo\Google Drive\Esperanza\Almacen\Backup\My Project\AssemblyInfo.vb">
</Event><Event ErrorLevel="0" Project="Almacen" Source="My Project\Application.Designer.vb" Description="Se realizó correctamente la copia de seguridad del archivo C:\Users\Eduardo\Google Drive\Esperanza\Almacen\Backup\My Project\Application.Designer.vb">
</Event><Event ErrorLevel="0" Project="Almacen" Source="My Project\Resources.Designer.vb" Description="Se realizó correctamente la copia de seguridad del archivo C:\Users\Eduardo\Google Drive\Esperanza\Almacen\Backup\My Project\Resources.Designer.vb">
</Event><Event ErrorLevel="0" Project="Almacen" Source="My Project\Settings.Designer.vb" Description="Se realizó correctamente la copia de seguridad del archivo C:\Users\Eduardo\Google Drive\Esperanza\Almacen\Backup\My Project\Settings.Designer.vb">
</Event><Event ErrorLevel="0" Project="Almacen" Source="configurar.Designer.vb" Description="Se realizó correctamente la copia de seguridad del archivo C:\Users\Eduardo\Google Drive\Esperanza\Almacen\Backup\configurar.Designer.vb">
</Event><Event ErrorLevel="0" Project="Almacen" Source="configurar.vb" Description="Se realizó correctamente la copia de seguridad del archivo C:\Users\Eduardo\Google Drive\Esperanza\Almacen\Backup\configurar.vb">
</Event><Event ErrorLevel="0" Project="Almacen" Source="Catalogo\productos.Designer.vb" Description="Se realizó correctamente la copia de seguridad del archivo C:\Users\Eduardo\Google Drive\Esperanza\Almacen\Backup\Catalogo\productos.Designer.vb">
</Event><Event ErrorLevel="0" Project="Almacen" Source="Catalogo\productos.vb" Description="Se realizó correctamente la copia de seguridad del archivo C:\Users\Eduardo\Google Drive\Esperanza\Almacen\Backup\Catalogo\productos.vb">
</Event><Event ErrorLevel="0" Project="Almacen" Source="Registro de  Inventarios por  lotes.Designer.vb" Description="Se realizó correctamente la copia de seguridad del archivo C:\Users\Eduardo\Google Drive\Esperanza\Almacen\Backup\Registro de  Inventarios por  lotes.Designer.vb">
</Event><Event ErrorLevel="0" Project="Almacen" Source="Registro de  Inventarios por  lotes.vb" Description="Se realizó correctamente la copia de seguridad del archivo C:\Users\Eduardo\Google Drive\Esperanza\Almacen\Backup\Registro de  Inventarios por  lotes.vb">
</Event><Event ErrorLevel="0" Project="Almacen" Source="Settings.vb" Description="Se realizó correctamente la copia de seguridad del archivo C:\Users\Eduardo\Google Drive\Esperanza\Almacen\Backup\Settings.vb">
</Event><Event ErrorLevel="0" Project="Almacen" Source="Surtidos\inventarios_movimientos.Designer.vb" Description="Se realizó correctamente la copia de seguridad del archivo C:\Users\Eduardo\Google Drive\Esperanza\Almacen\Backup\Surtidos\inventarios_movimientos.Designer.vb">
</Event><Event ErrorLevel="0" Project="Almacen" Source="Surtidos\inventarios_movimientos.vb" Description="Se realizó correctamente la copia de seguridad del archivo C:\Users\Eduardo\Google Drive\Esperanza\Almacen\Backup\Surtidos\inventarios_movimientos.vb">
</Event><Event ErrorLevel="0" Project="Almacen" Source="Surtidos\inv_reporte_existencias.Designer.vb" Description="Se realizó correctamente la copia de seguridad del archivo C:\Users\Eduardo\Google Drive\Esperanza\Almacen\Backup\Surtidos\inv_reporte_existencias.Designer.vb">
</Event><Event ErrorLevel="0" Project="Almacen" Source="Surtidos\inv_reporte_existencias.vb" Description="Se realizó correctamente la copia de seguridad del archivo C:\Users\Eduardo\Google Drive\Esperanza\Almacen\Backup\Surtidos\inv_reporte_existencias.vb">
</Event><Event ErrorLevel="0" Project="Almacen" Source="Surtidos\kardex_consumos.Designer.vb" Description="Se realizó correctamente la copia de seguridad del archivo C:\Users\Eduardo\Google Drive\Esperanza\Almacen\Backup\Surtidos\kardex_consumos.Designer.vb">
</Event><Event ErrorLevel="0" Project="Almacen" Source="Surtidos\kardex_consumos.vb" Description="Se realizó correctamente la copia de seguridad del archivo C:\Users\Eduardo\Google Drive\Esperanza\Almacen\Backup\Surtidos\kardex_consumos.vb">
</Event><Event ErrorLevel="0" Project="Almacen" Source="Surtidos\reporte_Consulta_Externa.Designer.vb" Description="Se realizó correctamente la copia de seguridad del archivo C:\Users\Eduardo\Google Drive\Esperanza\Almacen\Backup\Surtidos\reporte_Consulta_Externa.Designer.vb">
</Event><Event ErrorLevel="0" Project="Almacen" Source="Surtidos\reporte_Consulta_Externa.vb" Description="Se realizó correctamente la copia de seguridad del archivo C:\Users\Eduardo\Google Drive\Esperanza\Almacen\Backup\Surtidos\reporte_Consulta_Externa.vb">
</Event><Event ErrorLevel="0" Project="Almacen" Source="Surtidos\solicitud_nueva.designer.vb" Description="Se realizó correctamente la copia de seguridad del archivo C:\Users\Eduardo\Google Drive\Esperanza\Almacen\Backup\Surtidos\solicitud_nueva.designer.vb">
</Event><Event ErrorLevel="0" Project="Almacen" Source="Surtidos\solicitud_nueva.vb" Description="Se realizó correctamente la copia de seguridad del archivo C:\Users\Eduardo\Google Drive\Esperanza\Almacen\Backup\Surtidos\solicitud_nueva.vb">
</Event><Event ErrorLevel="0" Project="Almacen" Source="Stocks\Stock_por_ Area.Designer.vb" Description="Se realizó correctamente la copia de seguridad del archivo C:\Users\Eduardo\Google Drive\Esperanza\Almacen\Backup\Stocks\Stock_por_ Area.Designer.vb">
</Event><Event ErrorLevel="0" Project="Almacen" Source="Stocks\Stock_por_ Area.vb" Description="Se realizó correctamente la copia de seguridad del archivo C:\Users\Eduardo\Google Drive\Esperanza\Almacen\Backup\Stocks\Stock_por_ Area.vb">
</Event><Event ErrorLevel="0" Project="Almacen" Source="Surtidos\solicitud_reporte.Designer.vb" Description="Se realizó correctamente la copia de seguridad del archivo C:\Users\Eduardo\Google Drive\Esperanza\Almacen\Backup\Surtidos\solicitud_reporte.Designer.vb">
</Event><Event ErrorLevel="0" Project="Almacen" Source="Surtidos\solicitud_reporte.vb" Description="Se realizó correctamente la copia de seguridad del archivo C:\Users\Eduardo\Google Drive\Esperanza\Almacen\Backup\Surtidos\solicitud_reporte.vb">
</Event><Event ErrorLevel="0" Project="Almacen" Source="Surtidos\solicitud_solicitar.Designer.vb" Description="Se realizó correctamente la copia de seguridad del archivo C:\Users\Eduardo\Google Drive\Esperanza\Almacen\Backup\Surtidos\solicitud_solicitar.Designer.vb">
</Event><Event ErrorLevel="0" Project="Almacen" Source="Surtidos\solicitud_solicitar.vb" Description="Se realizó correctamente la copia de seguridad del archivo C:\Users\Eduardo\Google Drive\Esperanza\Almacen\Backup\Surtidos\solicitud_solicitar.vb">
</Event><Event ErrorLevel="0" Project="Almacen" Source="app.config" Description="Se realizó correctamente la copia de seguridad del archivo C:\Users\Eduardo\Google Drive\Esperanza\Almacen\Backup\app.config">
</Event><Event ErrorLevel="0" Project="Almacen" Source="My Project\Application.myapp" Description="Se realizó correctamente la copia de seguridad del archivo C:\Users\Eduardo\Google Drive\Esperanza\Almacen\Backup\My Project\Application.myapp">
</Event><Event ErrorLevel="0" Project="Almacen" Source="My Project\Settings.settings" Description="Se realizó correctamente la copia de seguridad del archivo C:\Users\Eduardo\Google Drive\Esperanza\Almacen\Backup\My Project\Settings.settings">
</Event><Event ErrorLevel="0" Project="Almacen" Source="recetas_dataset.xsc" Description="Se realizó correctamente la copia de seguridad del archivo C:\Users\Eduardo\Google Drive\Esperanza\Almacen\Backup\recetas_dataset.xsc">
</Event><Event ErrorLevel="0" Project="Almacen" Source="recetas_dataset.xsd" Description="Se realizó correctamente la copia de seguridad del archivo C:\Users\Eduardo\Google Drive\Esperanza\Almacen\Backup\recetas_dataset.xsd">
</Event><Event ErrorLevel="0" Project="Almacen" Source="recetas_dataset.xss" Description="Se realizó correctamente la copia de seguridad del archivo C:\Users\Eduardo\Google Drive\Esperanza\Almacen\Backup\recetas_dataset.xss">
</Event><Event ErrorLevel="0" Project="Almacen" Source="Resources\Binoculars.png" Description="Se realizó correctamente la copia de seguridad del archivo C:\Users\Eduardo\Google Drive\Esperanza\Almacen\Backup\Resources\Binoculars.png">
</Event><Event ErrorLevel="0" Project="Almacen" Source="Resources\Virtualbox.png" Description="Se realizó correctamente la copia de seguridad del archivo C:\Users\Eduardo\Google Drive\Esperanza\Almacen\Backup\Resources\Virtualbox.png">
</Event><Event ErrorLevel="0" Project="Almacen" Source="Resources\orden.jpg" Description="Se realizó correctamente la copia de seguridad del archivo C:\Users\Eduardo\Google Drive\Esperanza\Almacen\Backup\Resources\orden.jpg">
</Event><Event ErrorLevel="0" Project="Almacen" Source="Resources\medico.jpg" Description="Se realizó correctamente la copia de seguridad del archivo C:\Users\Eduardo\Google Drive\Esperanza\Almacen\Backup\Resources\medico.jpg">
</Event><Event ErrorLevel="0" Project="Almacen" Source="Resources\Note Book.png" Description="Se realizó correctamente la copia de seguridad del archivo C:\Users\Eduardo\Google Drive\Esperanza\Almacen\Backup\Resources\Note Book.png">
</Event><Event ErrorLevel="0" Project="Almacen" Source="Resources\Folder green.png" Description="Se realizó correctamente la copia de seguridad del archivo C:\Users\Eduardo\Google Drive\Esperanza\Almacen\Backup\Resources\Folder green.png">
</Event><Event ErrorLevel="0" Project="Almacen" Source="Resources\icono_medicamento.png" Description="Se realizó correctamente la copia de seguridad del archivo C:\Users\Eduardo\Google Drive\Esperanza\Almacen\Backup\Resources\icono_medicamento.png">
</Event><Event ErrorLevel="0" Project="Almacen" Source="Resources\Printer.png" Description="Se realizó correctamente la copia de seguridad del archivo C:\Users\Eduardo\Google Drive\Esperanza\Almacen\Backup\Resources\Printer.png">
</Event><Event ErrorLevel="0" Project="Almacen" Source="Resources\Error.png" Description="Se realizó correctamente la copia de seguridad del archivo C:\Users\Eduardo\Google Drive\Esperanza\Almacen\Backup\Resources\Error.png">
</Event><Event ErrorLevel="0" Project="Almacen" Source="Almacen_TemporaryKey.pfx" Description="Se realizó correctamente la copia de seguridad del archivo C:\Users\Eduardo\Google Drive\Esperanza\Almacen\Backup\Almacen_TemporaryKey.pfx">
</Event><Event ErrorLevel="0" Project="Almacen" Source="Resources\Log Off.png" Description="Se realizó correctamente la copia de seguridad del archivo C:\Users\Eduardo\Google Drive\Esperanza\Almacen\Backup\Resources\Log Off.png">
</Event><Event ErrorLevel="0" Project="Almacen" Source="Resources\Vmware.png" Description="Se realizó correctamente la copia de seguridad del archivo C:\Users\Eduardo\Google Drive\Esperanza\Almacen\Backup\Resources\Vmware.png">
</Event><Event ErrorLevel="0" Project="Almacen" Source="Resources\Vista Internet Sharing.png" Description="Se realizó correctamente la copia de seguridad del archivo C:\Users\Eduardo\Google Drive\Esperanza\Almacen\Backup\Resources\Vista Internet Sharing.png">
</Event><Event ErrorLevel="0" Project="Almacen" Source="Resources\Settings 1.png" Description="Se realizó correctamente la copia de seguridad del archivo C:\Users\Eduardo\Google Drive\Esperanza\Almacen\Backup\Resources\Settings 1.png">
</Event><Event ErrorLevel="0" Project="Almacen" Source="Resources\Save Copy.png" Description="Se realizó correctamente la copia de seguridad del archivo C:\Users\Eduardo\Google Drive\Esperanza\Almacen\Backup\Resources\Save Copy.png">
</Event><Event ErrorLevel="0" Project="Almacen" Source="Resources\Registry Mechanic.png" Description="Se realizó correctamente la copia de seguridad del archivo C:\Users\Eduardo\Google Drive\Esperanza\Almacen\Backup\Resources\Registry Mechanic.png">
</Event><Event ErrorLevel="0" Project="Almacen" Source="Resources\Vista Options.png" Description="Se realizó correctamente la copia de seguridad del archivo C:\Users\Eduardo\Google Drive\Esperanza\Almacen\Backup\Resources\Vista Options.png">
</Event><Event ErrorLevel="0" Project="Almacen" Source="clinicaDataSet.xsc" Description="Se realizó correctamente la copia de seguridad del archivo C:\Users\Eduardo\Google Drive\Esperanza\Almacen\Backup\clinicaDataSet.xsc">
</Event><Event ErrorLevel="0" Project="Almacen" Source="clinicaDataSet.xsd" Description="Se realizó correctamente la copia de seguridad del archivo C:\Users\Eduardo\Google Drive\Esperanza\Almacen\Backup\clinicaDataSet.xsd">
</Event><Event ErrorLevel="0" Project="Almacen" Source="clinicaDataSet.xss" Description="Se realizó correctamente la copia de seguridad del archivo C:\Users\Eduardo\Google Drive\Esperanza\Almacen\Backup\clinicaDataSet.xss">
</Event><Event ErrorLevel="0" Project="Almacen" Source="Resources\Registry.png" Description="Se realizó correctamente la copia de seguridad del archivo C:\Users\Eduardo\Google Drive\Esperanza\Almacen\Backup\Resources\Registry.png">
</Event><Event ErrorLevel="0" Project="Almacen" Source="Resources\Games 3.png" Description="Se realizó correctamente la copia de seguridad del archivo C:\Users\Eduardo\Google Drive\Esperanza\Almacen\Backup\Resources\Games 3.png">
</Event><Event ErrorLevel="0" Project="Almacen" Source="clinica.mdb" Description="Se realizó correctamente la copia de seguridad del archivo C:\Users\Eduardo\Google Drive\Esperanza\Almacen\Backup\clinica.mdb">
</Event><Event ErrorLevel="0" Project="Almacen" Source="Catalogo\Agrupar_productos.resx" Description="Se realizó correctamente la copia de seguridad del archivo C:\Users\Eduardo\Google Drive\Esperanza\Almacen\Backup\Catalogo\Agrupar_productos.resx">
</Event><Event ErrorLevel="0" Project="Almacen" Source="Catalogo\Medicos.resx" Description="Se realizó correctamente la copia de seguridad del archivo C:\Users\Eduardo\Google Drive\Esperanza\Almacen\Backup\Catalogo\Medicos.resx">
</Event><Event ErrorLevel="0" Project="Almacen" Source="Catalogo\productos_nuevo.resx" Description="Se realizó correctamente la copia de seguridad del archivo C:\Users\Eduardo\Google Drive\Esperanza\Almacen\Backup\Catalogo\productos_nuevo.resx">
</Event><Event ErrorLevel="0" Project="Almacen" Source="Catalogo\productos_relacion.resx" Description="Se realizó correctamente la copia de seguridad del archivo C:\Users\Eduardo\Google Drive\Esperanza\Almacen\Backup\Catalogo\productos_relacion.resx">
</Event><Event ErrorLevel="0" Project="Almacen" Source="compras\entradas_nueva.resx" Description="Se realizó correctamente la copia de seguridad del archivo C:\Users\Eduardo\Google Drive\Esperanza\Almacen\Backup\compras\entradas_nueva.resx">
</Event><Event ErrorLevel="0" Project="Almacen" Source="compras\Entrasdas_consulta.resx" Description="Se realizó correctamente la copia de seguridad del archivo C:\Users\Eduardo\Google Drive\Esperanza\Almacen\Backup\compras\Entrasdas_consulta.resx">
</Event><Event ErrorLevel="0" Project="Almacen" Source="configurar.resx" Description="Se realizó correctamente la copia de seguridad del archivo C:\Users\Eduardo\Google Drive\Esperanza\Almacen\Backup\configurar.resx">
</Event><Event ErrorLevel="0" Project="Almacen" Source="inventarios\capturar_inventarios.resx" Description="Se realizó correctamente la copia de seguridad del archivo C:\Users\Eduardo\Google Drive\Esperanza\Almacen\Backup\inventarios\capturar_inventarios.resx">
</Event><Event ErrorLevel="0" Project="Almacen" Source="inventarios\inventarios_hojas.resx" Description="Se realizó correctamente la copia de seguridad del archivo C:\Users\Eduardo\Google Drive\Esperanza\Almacen\Backup\inventarios\inventarios_hojas.resx">
</Event><Event ErrorLevel="0" Project="Almacen" Source="inventarios\inv_calcula_Existencia.resx" Description="Se realizó correctamente la copia de seguridad del archivo C:\Users\Eduardo\Google Drive\Esperanza\Almacen\Backup\inventarios\inv_calcula_Existencia.resx">
</Event><Event ErrorLevel="0" Project="Almacen" Source="inventarios\Inv_crear_hoja.resx" Description="Se realizó correctamente la copia de seguridad del archivo C:\Users\Eduardo\Google Drive\Esperanza\Almacen\Backup\inventarios\Inv_crear_hoja.resx">
</Event><Event ErrorLevel="0" Project="Almacen" Source="inventarios\lista_para_inventarios.rdlc" Description="Se realizó correctamente la copia de seguridad del archivo C:\Users\Eduardo\Google Drive\Esperanza\Almacen\Backup\inventarios\lista_para_inventarios.rdlc">
</Event><Event ErrorLevel="0" Project="Almacen" Source="inventarios\Existencias_al_momento.rdlc" Description="Se realizó correctamente la copia de seguridad del archivo C:\Users\Eduardo\Google Drive\Esperanza\Almacen\Backup\inventarios\Existencias_al_momento.rdlc">
</Event><Event ErrorLevel="0" Project="Almacen" Source="inventarios\reporte_de_inventario.resx" Description="Se realizó correctamente la copia de seguridad del archivo C:\Users\Eduardo\Google Drive\Esperanza\Almacen\Backup\inventarios\reporte_de_inventario.resx">
</Event><Event ErrorLevel="0" Project="Almacen" Source="inventarios\kardex.resx" Description="Se realizó correctamente la copia de seguridad del archivo C:\Users\Eduardo\Google Drive\Esperanza\Almacen\Backup\inventarios\kardex.resx">
</Event><Event ErrorLevel="0" Project="Almacen" Source="recetas\lotes_modificar_fechas.resx" Description="Se realizó correctamente la copia de seguridad del archivo C:\Users\Eduardo\Google Drive\Esperanza\Almacen\Backup\recetas\lotes_modificar_fechas.resx">
</Event><Event ErrorLevel="0" Project="Almacen" Source="recetas\recetas.resx" Description="Se realizó correctamente la copia de seguridad del archivo C:\Users\Eduardo\Google Drive\Esperanza\Almacen\Backup\recetas\recetas.resx">
</Event><Event ErrorLevel="0" Project="Almacen" Source="recetas\recetas_Asignar.resx" Description="Se realizó correctamente la copia de seguridad del archivo C:\Users\Eduardo\Google Drive\Esperanza\Almacen\Backup\recetas\recetas_Asignar.resx">
</Event><Event ErrorLevel="0" Project="Almacen" Source="recetas\recetas_modificar.resx" Description="Se realizó correctamente la copia de seguridad del archivo C:\Users\Eduardo\Google Drive\Esperanza\Almacen\Backup\recetas\recetas_modificar.resx">
</Event><Event ErrorLevel="0" Project="Almacen" Source="recetas\recetas_poner_factura.resx" Description="Se realizó correctamente la copia de seguridad del archivo C:\Users\Eduardo\Google Drive\Esperanza\Almacen\Backup\recetas\recetas_poner_factura.resx">
</Event><Event ErrorLevel="0" Project="Almacen" Source="Stocks\Hoja_de_gastos.rdlc" Description="Se realizó correctamente la copia de seguridad del archivo C:\Users\Eduardo\Google Drive\Esperanza\Almacen\Backup\Stocks\Hoja_de_gastos.rdlc">
</Event><Event ErrorLevel="0" Project="Almacen" Source="Stocks\hoja_gastos.resx" Description="Se realizó correctamente la copia de seguridad del archivo C:\Users\Eduardo\Google Drive\Esperanza\Almacen\Backup\Stocks\hoja_gastos.resx">
</Event><Event ErrorLevel="0" Project="Almacen" Source="Stocks\hoja_honorarios.resx" Description="Se realizó correctamente la copia de seguridad del archivo C:\Users\Eduardo\Google Drive\Esperanza\Almacen\Backup\Stocks\hoja_honorarios.resx">
</Event><Event ErrorLevel="0" Project="Almacen" Source="Stocks\hoja_honorarios_pediatricos.resx" Description="Se realizó correctamente la copia de seguridad del archivo C:\Users\Eduardo\Google Drive\Esperanza\Almacen\Backup\Stocks\hoja_honorarios_pediatricos.resx">
</Event><Event ErrorLevel="0" Project="Almacen" Source="Stocks\Report1.rdlc" Description="Se realizó correctamente la copia de seguridad del archivo C:\Users\Eduardo\Google Drive\Esperanza\Almacen\Backup\Stocks\Report1.rdlc">
</Event><Event ErrorLevel="0" Project="Almacen" Source="Stocks\stocks_definir.resx" Description="Se realizó correctamente la copia de seguridad del archivo C:\Users\Eduardo\Google Drive\Esperanza\Almacen\Backup\Stocks\stocks_definir.resx">
</Event><Event ErrorLevel="0" Project="Almacen" Source="Surtidos\consultar_consumo_de_consumibles.resx" Description="Se realizó correctamente la copia de seguridad del archivo C:\Users\Eduardo\Google Drive\Esperanza\Almacen\Backup\Surtidos\consultar_consumo_de_consumibles.resx">
</Event><Event ErrorLevel="0" Project="Almacen" Source="Surtidos\Consumos.resx" Description="Se realizó correctamente la copia de seguridad del archivo C:\Users\Eduardo\Google Drive\Esperanza\Almacen\Backup\Surtidos\Consumos.resx">
</Event><Event ErrorLevel="0" Project="Almacen" Source="main.resx" Description="Se realizó correctamente la copia de seguridad del archivo C:\Users\Eduardo\Google Drive\Esperanza\Almacen\Backup\main.resx">
</Event><Event ErrorLevel="0" Project="Almacen" Source="My Project\Resources.resx" Description="Se realizó correctamente la copia de seguridad del archivo C:\Users\Eduardo\Google Drive\Esperanza\Almacen\Backup\My Project\Resources.resx">
</Event><Event ErrorLevel="0" Project="Almacen" Source="Catalogo\productos.resx" Description="Se realizó correctamente la copia de seguridad del archivo C:\Users\Eduardo\Google Drive\Esperanza\Almacen\Backup\Catalogo\productos.resx">
</Event><Event ErrorLevel="0" Project="Almacen" Source="Registro de  Inventarios por  lotes.resx" Description="Se realizó correctamente la copia de seguridad del archivo C:\Users\Eduardo\Google Drive\Esperanza\Almacen\Backup\Registro de  Inventarios por  lotes.resx">
</Event><Event ErrorLevel="0" Project="Almacen" Source="Surtidos\hoja_entrega.rdlc" Description="Se realizó correctamente la copia de seguridad del archivo C:\Users\Eduardo\Google Drive\Esperanza\Almacen\Backup\Surtidos\hoja_entrega.rdlc">
</Event><Event ErrorLevel="0" Project="Almacen" Source="Surtidos\inventarios_movimientos.resx" Description="Se realizó correctamente la copia de seguridad del archivo C:\Users\Eduardo\Google Drive\Esperanza\Almacen\Backup\Surtidos\inventarios_movimientos.resx">
</Event><Event ErrorLevel="0" Project="Almacen" Source="Surtidos\inv_reporte_existencias.resx" Description="Se realizó correctamente la copia de seguridad del archivo C:\Users\Eduardo\Google Drive\Esperanza\Almacen\Backup\Surtidos\inv_reporte_existencias.resx">
</Event><Event ErrorLevel="0" Project="Almacen" Source="Surtidos\kardex_consumos.resx" Description="Se realizó correctamente la copia de seguridad del archivo C:\Users\Eduardo\Google Drive\Esperanza\Almacen\Backup\Surtidos\kardex_consumos.resx">
</Event><Event ErrorLevel="0" Project="Almacen" Source="Surtidos\inv_existenciasal31.rdlc" Description="Se realizó correctamente la copia de seguridad del archivo C:\Users\Eduardo\Google Drive\Esperanza\Almacen\Backup\Surtidos\inv_existenciasal31.rdlc">
</Event><Event ErrorLevel="0" Project="Almacen" Source="Surtidos\reporte_consulta_externa.rdlc" Description="Se realizó correctamente la copia de seguridad del archivo C:\Users\Eduardo\Google Drive\Esperanza\Almacen\Backup\Surtidos\reporte_consulta_externa.rdlc">
</Event><Event ErrorLevel="0" Project="Almacen" Source="Surtidos\reporte_Consulta_Externa.resx" Description="Se realizó correctamente la copia de seguridad del archivo C:\Users\Eduardo\Google Drive\Esperanza\Almacen\Backup\Surtidos\reporte_Consulta_Externa.resx">
</Event><Event ErrorLevel="0" Project="Almacen" Source="Surtidos\reporte_de_consumibles.rdlc" Description="Se realizó correctamente la copia de seguridad del archivo C:\Users\Eduardo\Google Drive\Esperanza\Almacen\Backup\Surtidos\reporte_de_consumibles.rdlc">
</Event><Event ErrorLevel="0" Project="Almacen" Source="Surtidos\solicitud_solicitar.resx" Description="Se realizó correctamente la copia de seguridad del archivo C:\Users\Eduardo\Google Drive\Esperanza\Almacen\Backup\Surtidos\solicitud_solicitar.resx">
</Event><Event ErrorLevel="0" Project="Almacen" Source="Surtidos\surtido.rdlc" Description="Se realizó correctamente la copia de seguridad del archivo C:\Users\Eduardo\Google Drive\Esperanza\Almacen\Backup\Surtidos\surtido.rdlc">
</Event><Event ErrorLevel="0" Project="Almacen" Source="Surtidos\solicitud_nueva.resx" Description="Se realizó correctamente la copia de seguridad del archivo C:\Users\Eduardo\Google Drive\Esperanza\Almacen\Backup\Surtidos\solicitud_nueva.resx">
</Event><Event ErrorLevel="0" Project="Almacen" Source="Stocks\Stocks.rdlc" Description="Se realizó correctamente la copia de seguridad del archivo C:\Users\Eduardo\Google Drive\Esperanza\Almacen\Backup\Stocks\Stocks.rdlc">
</Event><Event ErrorLevel="0" Project="Almacen" Source="Stocks\Stock_por_ Area.resx" Description="Se realizó correctamente la copia de seguridad del archivo C:\Users\Eduardo\Google Drive\Esperanza\Almacen\Backup\Stocks\Stock_por_ Area.resx">
</Event><Event ErrorLevel="0" Project="Almacen" Source="Surtidos\solicitud_reporte.resx" Description="Se realizó correctamente la copia de seguridad del archivo C:\Users\Eduardo\Google Drive\Esperanza\Almacen\Backup\Surtidos\solicitud_reporte.resx">
</Event><Event ErrorLevel="1" Project="Almacen" Source="Almacen.vbproj" Description="La versión de destino de su proyecto es .NET Framework 2.0 ó 3.0. Si el proyecto utiliza ensamblados que requieren una versión más reciente de .NET Framework, no se podrá compilar. Puede cambiar la versión de .NET Framework haciendo clic en Propiedades en el menú del proyecto y seleccionando una nueva versión en el cuadro desplegable '.NET Framework'. (En Visual Basic, haga clic en el botón 'Opciones avanzadas del compilador...' en la pestaña Compilar).">
</Event><Event ErrorLevel="0" Project="Almacen" Source="Almacen.vbproj" Description="Proyecto convertido correctamente">
</Event><Event ErrorLevel="3" Project="Almacen" Source="Almacen.vbproj" Description="Converted">
</Event><Event ErrorLevel="0" Project="" Source="Almacen.sln" Description="La solución se convirtió correctamente">
</Event><Event ErrorLevel="3" Project="" Source="Almacen.sln" Description="Converted">
</Event><Event ErrorLevel="0" Project="Almacen" Source="Almacen.vbproj" Description="Examen completo: no es necesario actualizar los archivos de proyecto.">
</Event></UpgradeLog>